MANIFEST.in
README.txt
VERSION.txt
setup.py
repoze/__init__.py
repoze.what.plugins.ini.egg-info/PKG-INFO
repoze.what.plugins.ini.egg-info/SOURCES.txt
repoze.what.plugins.ini.egg-info/dependency_links.txt
repoze.what.plugins.ini.egg-info/entry_points.txt
repoze.what.plugins.ini.egg-info/namespace_packages.txt
repoze.what.plugins.ini.egg-info/not-zip-safe
repoze.what.plugins.ini.egg-info/requires.txt
repoze.what.plugins.ini.egg-info/top_level.txt
repoze/what/__init__.py
repoze/what/plugins/__init__.py
repoze/what/plugins/ini/__init__.py
repoze/what/plugins/ini/ini.py
repoze/what/plugins/ini/parser.py
tests/__init__.py
tests/groups.ini
tests/permissions.ini
tests/test_parser.py
tests/test_plugin_ini.py