Metadata-Version: 1.0
Name: repoze.what.plugins.ini
Version: 0.2.2
Summary: repoze.what pluggin with sources based on INI files.
Home-page: http://github.com/jdinuncio/repoze.what.plugins.ini/tree/master
Author: Jose Dinuncio
Author-email: jdinunci@uc.edu.ve
License: BSD-derived (see http://www.repoze.org/LICENSE.txt)
Keywords: wsgi repoze what pluggins authorization INI ini
Platform: UNKNOWN
